pygicord/__init__.py
pygicord/base.py
pygicord/control.py
pygicord/enums.py
pygicord/exceptions.py
pygicord/paginator.py
pygicord/utils.py
pygicord-1.1.3.dist-info/LICENSE
pygicord-1.1.3.dist-info/METADATA
pygicord-1.1.3.dist-info/WHEEL
pygicord-1.1.3.dist-info/top_level.txt
pygicord-1.1.3.dist-info/RECORD
