Metadata-Version: 2.1
Name: pygicord
Version: 1.1.3
Summary: A pagination wrapper for discord.py
Home-page: https://github.com/davidetacchini/pygicord
Author: Davide Tacchini
License: MIT
Keywords: discord.py,paginator
Classifier: Programming Language :: Python :: 3.7
Classifier: Programming Language :: Python :: 3.8
Classifier: Programming Language :: Python :: 3.9
Classifier: Natural Language :: English
Classifier: License :: OSI Approved :: MIT License
Classifier: Operating System :: OS Independent
Classifier: Topic :: Internet
Classifier: Topic :: Software Development :: Libraries
Classifier: Topic :: Software Development :: Libraries :: Python Modules
Classifier: Topic :: Utilities
Requires-Python: >=3.7.0
License-File: LICENSE
Requires-Dist: discord.py
Provides-Extra: dev
Requires-Dist: black ; extra == 'dev'
Requires-Dist: isort ; extra == 'dev'
Requires-Dist: flake8 ; extra == 'dev'
